scFates/__init__.py
scFates/logging.py
scFates/pl.py
scFates/pp.py
scFates/settings.py
scFates/tl.py
scFates/datasets/__init__.py
scFates/datasets/_datasets.py
scFates/datasets/test.h5ad
scFates/get/__init__.py
scFates/get/get.py
scFates/plot/__init__.py
scFates/plot/binned_pseudotime_meta.py
scFates/plot/covariate.py
scFates/plot/dendrogram.py
scFates/plot/features.py
scFates/plot/linearity_deviation.py
scFates/plot/matrix.py
scFates/plot/milestones.py
scFates/plot/module_inclusion.py
scFates/plot/modules.py
scFates/plot/palette_tools.py
scFates/plot/palettes.py
scFates/plot/slide_cors.py
scFates/plot/synchro_path.py
scFates/plot/test_association.py
scFates/plot/test_fork.py
scFates/plot/trajectory.py
scFates/plot/utils.py
scFates/preprocessing/__init__.py
scFates/preprocessing/diffusion.py
scFates/preprocessing/pagoda2.py
scFates/tests/test_w_plots.py
scFates/tools/__init__.py
scFates/tools/_test_monocle3.R
scFates/tools/bifurcation_tools.py
scFates/tools/cluster.py
scFates/tools/conversion.py
scFates/tools/correlation_tools.py
scFates/tools/covariate.py
scFates/tools/dendrogram.py
scFates/tools/fit.py
scFates/tools/graph_fitting.py
scFates/tools/graph_operations.py
scFates/tools/linearity_deviation.py
scFates/tools/pseudotime.py
scFates/tools/root.py
scFates/tools/slide_cors.py
scFates/tools/test_association.py
scFates/tools/utils.py
scfates-1.2.1.dist-info/licenses/LICENSE
scfates-1.2.1.dist-info/METADATA
scfates-1.2.1.dist-info/WHEEL
scfates-1.2.1.dist-info/top_level.txt
scfates-1.2.1.dist-info/RECORD
