Metadata-Version: 2.4
Name: scFates
Version: 1.2.1
Summary: scanpy compatible python suite for fast tree inference and advanced pseudotime downstream analysis
Author: Louis Faure
Project-URL: Repository, https://github.com/LouisFaure/scFates
Requires-Python: >=3.8
License-File: LICENSE
Requires-Dist: anndata>=0.7.4
Requires-Dist: seaborn>=0.11.0
Requires-Dist: tqdm>=4.45.0
Requires-Dist: numba>=0.51.2
Requires-Dist: scipy>=1.4.1
Requires-Dist: scanpy>=1.7.0
Requires-Dist: leidenalg>=0.8.1
Requires-Dist: numpy
Requires-Dist: joblib>=0.17.0
Requires-Dist: pandas>=2.2.3
Requires-Dist: statsmodels>=0.11.1
Requires-Dist: matplotlib
Requires-Dist: plotly>=4.8.1
Requires-Dist: cycler>=0.10.0
Requires-Dist: python_igraph>=0.8.2
Requires-Dist: typing_extensions
Requires-Dist: scikit-learn
Requires-Dist: scikit-misc
Requires-Dist: simpleppt>=1.1.3
Requires-Dist: elpigraph-python==0.3.2
Requires-Dist: networkx>3.0
Requires-Dist: igraph>=0.9.6
Requires-Dist: adjustText>=0.7.3
Dynamic: license-file
